sh3bang/__init__.py
sh3bang/cli.py
sh3bang/automation/__init__.py
sh3bang/automation/url_shortener.py
sh3bang/clipboard_manager/__init__.py
sh3bang/clipboard_manager/cli.py
sh3bang/clipboard_manager/core.py
sh3bang/clipboard_manager/storage.py
sh3bang/daily/__init__.py
sh3bang/daily/journal.py
sh3bang/daily/reminder.py
sh3bang/daily/todo.py
sh3bang/devtools/__init__.py
sh3bang/devtools/cli.py
sh3bang/devtools/envreader.py
sh3bang/devtools/portcheck.py
sh3bang/devtools/reqcheck.py
sh3bang/dsa/__init__.py
sh3bang/dsa/algorithms/__init__.py
sh3bang/dsa/data_structures/__init__.py
sh3bang/dsa/utils/__init__.py
sh3bang/files/__init__.py
sh3bang/files/cli.py
sh3bang/files/converter.py
sh3bang/files/duplicates.py
sh3bang/files/organizer.py
sh3bang/files/renamer.py
sh3bang/imgtool/__init__.py
sh3bang/imgtool/cli.py
sh3bang/imgtool/core.py
sh3bang-0.3.0.dist-info/licenses/LICENSE
sh3bang-0.3.0.dist-info/METADATA
sh3bang-0.3.0.dist-info/WHEEL
sh3bang-0.3.0.dist-info/entry_points.txt
sh3bang-0.3.0.dist-info/top_level.txt
sh3bang-0.3.0.dist-info/RECORD
