Metadata-Version: 2.4
Name: sh3bang
Version: 0.3.0
Summary: A personal CLI with utilities.
Author-email: Wasik Ahmed Apon <aponwasikahmed@gmail.com>
License: MIT
Project-URL: Homepage, https://github.com/wasikahmed/sh3bang
Project-URL: Issues, https://github.com/wasikahmed/sh3bang/issues
Keywords: cli,utilities,automation,tools,personal
Requires-Python: >=3.10
License-File: LICENSE
Requires-Dist: requests>=2.32.0
Requires-Dist: typer>=0.12.3
Requires-Dist: rich>=13.7.0
Requires-Dist: pdf2docx
Requires-Dist: docx2pdf
Requires-Dist: tabulate
Requires-Dist: pyperclip
Requires-Dist: pillow
Dynamic: license-file
